mdla/__init__.py
mdla/dict_metrics.py
mdla/mdla.py
mdla-1.0.2.dist-info/LICENSE
mdla-1.0.2.dist-info/WHEEL
mdla-1.0.2.dist-info/METADATA
mdla-1.0.2.dist-info/RECORD
