Metadata-Version: 2.1
Name: mdla
Version: 1.0.2
Summary: Multivariate Dictionary Learning Algorithm
Home-page: https://github.com/sylvchev/mdla
License: BSD-3-Clause
Keywords: sparse decomposition,dictionary learning,multivariate signal,eeg
Author: Sylvain Chevallier
Author-email: sylvain.chevallier@uvsq.fr
Requires-Python: >=3.7,<4.0
Classifier: Intended Audience :: Developers
Classifier: Intended Audience :: Science/Research
Classifier: License :: OSI Approved :: BSD License
Classifier: Programming Language :: Python :: 3
Classifier: Programming Language :: Python :: 3.10
Classifier: Programming Language :: Python :: 3.7
Classifier: Programming Language :: Python :: 3.8
Classifier: Programming Language :: Python :: 3.9
Classifier: Topic :: Scientific/Engineering :: Artificial Intelligence
Requires-Dist: cvxopt (>=1.2.0,<2.0.0)
Requires-Dist: matplotlib (>=3.0,<4.0)
Requires-Dist: numpy (>=1.19.0,<2.0.0)
Requires-Dist: scikit-learn (>=1.0,<2.0)
Requires-Dist: scipy (>=1.5,<2.0)
Project-URL: Documentation, http://github.com/sylvchev/mdla
Project-URL: Repository, https://github.com/sylvchev/mdla
